quantum_bell_api/__init__.py
quantum_bell_api/decoherence.py
quantum_bell_api/dejmps.py
quantum_bell_api/resources.py
quantum_bell_api/swapping.py
quantum_bell_api/utility.py
quantum_bell_api-0.1.0.dist-info/METADATA
quantum_bell_api-0.1.0.dist-info/WHEEL
quantum_bell_api-0.1.0.dist-info/top_level.txt
quantum_bell_api-0.1.0.dist-info/RECORD
