Metadata-Version: 2.1
Name: quantum_bell_api
Version: 0.1.0
Summary: A package implementing quantum algebraic operations on Bell diagonal states.
Home-page: https://github.com/LBacciottini/quantum_bell_api
Author: Leonardo Bacciottini
Author-email: baccio.leonardo@gmail.com
License: MIT
Platform: UNKNOWN
